auretrix/__init__.py
auretrix/exceptions.py
auretrix/languages.py
auretrix/speech.py
auretrix/transcribe.py
auretrix/utils.py
auretrix/providers/__init__.py
auretrix/providers/assemblyai.py
auretrix/providers/azure.py
auretrix/providers/base.py
auretrix/providers/google.py
auretrix/providers/whisper.py
auretrix-0.1.1.dist-info/licenses/LICENSE
auretrix-0.1.1.dist-info/METADATA
auretrix-0.1.1.dist-info/WHEEL
auretrix-0.1.1.dist-info/entry_points.txt
auretrix-0.1.1.dist-info/top_level.txt
auretrix-0.1.1.dist-info/RECORD
