Metadata-Version: 2.4
Name: auretrix
Version: 0.1.1
Summary: Unified speech recognition library with multi-provider support and Indian language focus
Home-page: https://github.com/auretrix/auretrix
Author: Ayush khatri
Author-email: Ayush khatri <auretrix07@gmail.com>
License: MIT License
Project-URL: Homepage, https://github.com/auretrix/auretrix
Project-URL: Documentation, https://docs.auretrix.com
Project-URL: Repository, https://github.com/auretrix/auretrix
Project-URL: Bug Tracker, https://github.com/auretrix/auretrix/issues
Keywords: speech recognition,whisper,google speech,assemblyai,azure,indian languages,hindi,transcription,speech-to-text,stt
Classifier: Development Status :: 3 - Alpha
Classifier: Intended Audience :: Developers
Classifier: License :: OSI Approved :: MIT License
Classifier: Programming Language :: Python :: 3
Classifier: Programming Language :: Python :: 3.8
Classifier: Programming Language :: Python :: 3.9
Classifier: Programming Language :: Python :: 3.10
Classifier: Programming Language :: Python :: 3.11
Classifier: Topic :: Multimedia :: Sound/Audio :: Speech
Classifier: Topic :: Scientific/Engineering :: Artificial Intelligence
Requires-Python: >=3.8
License-File: LICENSE
Requires-Dist: requests>=2.28.0
Requires-Dist: pydub>=0.25.1
Requires-Dist: numpy>=1.21.0
Provides-Extra: whisper
Requires-Dist: openai-whisper>=20230314; extra == "whisper"
Provides-Extra: google
Requires-Dist: google-cloud-speech>=2.20.0; extra == "google"
Provides-Extra: assemblyai
Requires-Dist: assemblyai>=0.17.0; extra == "assemblyai"
Provides-Extra: azure
Requires-Dist: azure-cognitiveservices-speech>=1.31.0; extra == "azure"
Provides-Extra: all
Requires-Dist: openai-whisper>=20230314; extra == "all"
Requires-Dist: google-cloud-speech>=2.20.0; extra == "all"
Requires-Dist: assemblyai>=0.17.0; extra == "all"
Requires-Dist: azure-cognitiveservices-speech>=1.31.0; extra == "all"
Provides-Extra: dev
Requires-Dist: pytest>=7.0.0; extra == "dev"
Requires-Dist: pytest-cov>=4.0.0; extra == "dev"
Requires-Dist: black>=22.0.0; extra == "dev"
Requires-Dist: flake8>=5.0.0; extra == "dev"
Requires-Dist: mypy>=0.990; extra == "dev"
Requires-Dist: twine>=4.0.0; extra == "dev"
Dynamic: author
Dynamic: home-page
Dynamic: license-file
Dynamic: requires-python
